pyvpacker.py
pyvpacker-1.1.data/scripts/demopacker.py
pyvpacker-1.1.dist-info/METADATA
pyvpacker-1.1.dist-info/WHEEL
pyvpacker-1.1.dist-info/entry_points.txt
pyvpacker-1.1.dist-info/top_level.txt
pyvpacker-1.1.dist-info/RECORD
