Metadata-Version: 2.1
Name: pyvpacker
Version: 1.1
Summary: Pack python data onto a string.
Home-page: https://github.com/pglen/pyvpacker
Author: Peter Glen
Author-email: peterglen99@gmail.com
Classifier: Programming Language :: Python :: 3
Classifier: License :: OSI Approved :: MIT License
Classifier: Operating System :: OS Independent
Requires-Python: >=3
